odoo/addons/purchase_request_cancel_confirm/README.rst
odoo/addons/purchase_request_cancel_confirm/__init__.py
odoo/addons/purchase_request_cancel_confirm/__manifest__.py
odoo/addons/purchase_request_cancel_confirm/i18n/es.po
odoo/addons/purchase_request_cancel_confirm/i18n/it.po
odoo/addons/purchase_request_cancel_confirm/i18n/purchase_request_cancel_confirm.pot
odoo/addons/purchase_request_cancel_confirm/model/__init__.py
odoo/addons/purchase_request_cancel_confirm/model/purchase_request.py
odoo/addons/purchase_request_cancel_confirm/readme/CONTRIBUTORS.md
odoo/addons/purchase_request_cancel_confirm/readme/DESCRIPTION.md
odoo/addons/purchase_request_cancel_confirm/static/description/icon.png
odoo/addons/purchase_request_cancel_confirm/static/description/index.html
odoo/addons/purchase_request_cancel_confirm/tests/__init__.py
odoo/addons/purchase_request_cancel_confirm/tests/test_purchase_request_cancel_confirm.py
odoo_addon_purchase_request_cancel_confirm-18.0.1.0.0.4.dist-info/METADATA
odoo_addon_purchase_request_cancel_confirm-18.0.1.0.0.4.dist-info/WHEEL
odoo_addon_purchase_request_cancel_confirm-18.0.1.0.0.4.dist-info/top_level.txt
odoo_addon_purchase_request_cancel_confirm-18.0.1.0.0.4.dist-info/RECORD
